omss/__init__.py
omss/alternatives.py
omss/configuration.py
omss/element.py
omss/matrix.py
omss/render.py
omss/rules.py
omss/rules_generator.py
omss/seed.py
omss-0.1.0.dist-info/licenses/LICENSE
omss-0.1.0.dist-info/METADATA
omss-0.1.0.dist-info/WHEEL
omss-0.1.0.dist-info/top_level.txt
omss-0.1.0.dist-info/RECORD
