Metadata-Version: 2.4
Name: omss
Version: 0.1.0
Summary: Python package for generating customizable matrix reasoning puzzles, inspired by Raven Progressive Matrices
Author-email: Aran van Hout <aranvanhout@hotmail.com>, Nicholas Judd <nicholas.judd@radboudumc.nl>
License:                     GNU GENERAL PUBLIC LICENSE
Project-URL: Homepage, https://github.com/aranvhout/OMSS_generator
Requires-Python: >=3.7
License-File: LICENSE
Requires-Dist: numpy==2.2.3
Requires-Dist: opencv-python==4.11.0.86
Requires-Dist: Pillow==11.2.1
Requires-Dist: matplotlib==3.10.3
Dynamic: license-file
